iris_axi/axi_ram.v
/// use this module to create a RAM with AXI-Stream interface
/// you are allowed to change the input interface to axi-lite if you want


module axi_ram (

    input aclk,
    input aresetn,

    // AXI-Stream Slave

    input [31:0]s_axis_tdata,
    input s_axis_tvalid,
    output reg s_axis_tready

    // AXI-Stream Master 

    // output reg [31:0]m_axis_tdata,
    // output reg m_axis_tvalid,
    // input m_axis_tready
    
);

reg [7:0] mem [0:288];
reg [7:0] number;
reg [7:0] count;
reg [2:0] count_bin;
reg [8:0] data_bin;  

wire ready;

assign ready = (count <= 8'h20);

integer i;

always @(posedge aclk) begin
    if(!aresetn) begin
        for(i=0;i<288;i=i+1) begin
            mem[i] <= 0;
        end
        number <= 0;
        count <= 0;
        count_bin <= 0;
        data_bin <= 0;
        s_axis_tready <= 1'b1;
    end
    if(!ready) s_axis_tready <=1'b0;


    
    if (s_axis_tvalid && s_axis_tready) begin
        {number, count, count_bin, data_bin} <= s_axis_tdata[27:0];
        mem[count_bin<<2] <= count;
        mem[data_bin] <= number;
    end
end

// Do the master implementation


endmodule

iris_axi/s_m_hist.v
//////////////////////////////////////////////////////////////////////////////////////////////////
////      Edit to create a block to create a data processing block, which takes in data //////////
/// from the lfsr through a AXI-Stream slave interface, and categorises them into bins  //////////
/////      The output data includes the  count value of numbers in each bin and data    //////////
////     + address in ram , which the data is supposed to be written to as provided in  //////////
////                            the address map below                                   //////////
////     The output data is to sent out through a AXI-Stream master/AXI-Lite interface.    ///////
//////////////////////////////////////////////////////////////////////////////////////////////////


//  -------------------------------------------------
//  | Bin Number |    Range of Values               |
//  -------------------------------------------------
//  | Bin 0      |        1   -  32                 |
//  | Bin 1      |       33   -  64                 |
//  | Bin 2      |       65   -  96                 |
//  | Bin 3      |       97   - 128                 |
//  | Bin 4      |      129   - 160                 |
//  | Bin 5      |      161   - 192                 |
//  | Bin 6      |      193   - 224                 |
//  | Bin 7      |      225   - 255                 |
//  -------------------------------------------------


// assume the ram to be 0x120 x 8 bit 

// ----------------------------------------------------------------------------------------
// | Address Range     | Register / Memory     | Description                              |
// ----------------------------------------------------------------------------------------
// | 0x00              | Bin 0 Count           | Count for values in range 1-32           |
// | 0x04              | Bin 1 Count           | Count for values in range 33-64          |
// | 0x08              | Bin 2 Count           | Count for values in range 65-96          |
// | 0x0C              | Bin 3 Count           | Count for values in range 97-128         |
// | 0x10              | Bin 4 Count           | Count for values in range 129-160        |
// | 0x14              | Bin 5 Count           | Count for values in range 161-192        |
// | 0x18              | Bin 6 Count           | Count for values in range 193-224        |
// | 0x1C              | Bin 7 Count           | Count for values in range 225-255        |
// ----------------------------------------------------------------------------------------
// | 0x20 - 0x3F       | Bin 0 Data Storage    | Stores values belonging to Bin 0         |
// | 0x40 - 0x5F       | Bin 1 Data Storage    | Stores values belonging to Bin 1         |
// | 0x60 - 0x7F       | Bin 2 Data Storage    | Stores values belonging to Bin 2         |
// | 0x80 - 0x9F       | Bin 3 Data Storage    | Stores values belonging to Bin 3         |
// | 0xA0 - 0xBF       | Bin 4 Data Storage    | Stores values belonging to Bin 4         |
// | 0xC0 - 0xDF       | Bin 5 Data Storage    | Stores values belonging to Bin 5         |
// | 0xE0 - 0xFF       | Bin 6 Data Storage    | Stores values belonging to Bin 6         |
// | 0x100 - 0x11F     | Bin 7 Data Storage    | Stores values belonging to Bin 7         |
// ----------------------------------------------------------------------------------------





module s_m_hist (

    input aclk,
    input aresetn,

    // AXI-Stream Slave

    input [31:0]s_axis_tdata,
    input s_axis_tvalid,
    output reg s_axis_tready,

    // AXI-Stream Master 

    output reg [31:0]m_axis_tdata,
    output reg m_axis_tvalid,
    input m_axis_tready
    
);
    //HIST
    reg [7:0] count;
    reg [2:0] count_bin; // Bin index (0-7)
    reg [8:0] data_bin;   // Bin value + base address

    //Slave side
    reg [7:0] number; // Changed to 8-bit input

    //Slave side
    always @(posedge aclk) begin
        if (!aresetn) begin
            s_axis_tready <= m_axis_tready;
            count <= 8'b0;
            count_bin <= 3'b0;
            data_bin <= 9'b0;

        end else s_axis_tready <= m_axis_tready;
        
        if (s_axis_tvalid && s_axis_tready) begin
            number <= s_axis_tdata[7:0]; // Assuming the data is in the lower 8 bits
        end
    end
    


        
//Master side
    always @(posedge aclk) begin
        if(!aresetn) begin
            m_axis_tvalid <= 1'b0;
            m_axis_tdata <= 32'b0;
        end 
        if(s_axis_tvalid) m_axis_tvalid <= 1'b1;
        if (m_axis_tready && m_axis_tvalid) begin
            m_axis_tdata <= {4'b0, number, count, count_bin, data_bin}; // Send count and bin index
        end
    end


reg [7:0] bin [0:7];
    integer i;

    always @(posedge aclk or posedge aresetn) begin
        if (!aresetn) begin
            for ( i = 0; i < 8; i = i + 1) begin
                bin[i] <= 8'b0;
            end
            count <= 8'b0;
            count_bin <= 3'b0;
            data_bin <= 9'b0;
        end
        else if(m_axis_tready) begin
            if (number>=1 && number <= 32) begin
                bin[0] <= bin[0] + 1;
                count <= bin[0] + 1;
                count_bin <= 3'b000;
                data_bin <= 9'h020 + bin[0]; // Base address 0x20 + count
            end
            else if (number >=33 && number <= 64) begin
                bin[1] <= bin[1] + 1;
                count <= bin[1] + 1;
                count_bin <= 3'b001;
                data_bin <= 9'h040 + bin[1]; // Base address 0x40 + count
            end
            else if (number >= 65 && number <= 96) begin
                bin[2] <= bin[2] + 1;
                count <= bin[2] + 1;
                count_bin <= 3'b010;
                data_bin <= 9'h060 + bin[2];
            end
            else if (number >= 97 && number <= 128) begin
                bin[3] <= bin[3] + 1;
                count <= bin[3] + 1;
                count_bin <= 3'b011;
                data_bin <= 9'h080 + bin[3];
            end
            else if (number >= 129 && number <= 160) begin
                bin[4] <= bin[4] + 1;
                count <= bin[4] + 1;
                count_bin <= 3'b100;
                data_bin <= 9'h0A0 + bin[4];
            end
            else if (number >= 161 && number <= 192) begin
                bin[5] <= bin[5] + 1;
                count <= bin[5] + 1;
                count_bin <= 3'b101;
                data_bin <= 9'h0C0 + bin[5];
            end
            else if (number >= 193 && number <= 224) begin
                bin[6] <= bin[6] + 1;
                count <= bin[6] + 1;
                count_bin <= 3'b110;
                data_bin <= 9'h0E0 + bin[6];
            end
            else if (number==255 && number == 255) begin
                bin[7] <= bin[7] + 1;
                count <= bin[7] + 1;
                count_bin <= 3'b111;
                data_bin <= 9'h100 + bin[7]; // Base address 0x100 + count
            end
            else if(number == 0) begin end
        end
    end

endmodule

iris_axi/lfsr.v
// LFSR is a sequential circuit used to generate Pseudo- Random numbers. 
// Build an 8 bit LFSR with separate registers for start, stop , seed and
//  taps, interfaced with AXI-Lite slave (check files for more details).


module LFSR(
    input clk,
    input reset,
    input start,
    input stop,
    input [7:0] seed,
    input [1:8] taps,
    output wire [7:0] lfsr_out

);

    reg [1:8] regs;
    wire feedback;
    wire [1:8] a;
    assign a = regs & taps;
    assign feedback = ^a; 
    assign lfsr_out = regs;

    always @(posedge clk) begin
        if(!reset) begin
            regs <= seed;
        end
        else if(stop) begin
            regs <= seed;
        end
        else if(start && !stop) begin
            regs <= {feedback,regs[1:7]};
        end
    end

endmodule

iris_axi/saxl_lfsr.v
//////////////////////////////////////////////////////////////////////////////////
////      Edit to create a 8bit LFSR module with AXI-Lite interface          /////
/////      for register configuration and AX-Stream for lfsr output          /////
//////////////////////////////////////////////////////////////////////////////////


module s_axil #(
    parameter C_AXIL_ADDR_WIDTH = 4,
    parameter C_AXIL_DATA_WIDTH = 32
)(
    input aclk,
    input aresetn,

    // AXI-Lite Slave Interface
    input  [C_AXIL_ADDR_WIDTH-1:0] s_axi_awaddr,
    input                       s_axi_awvalid,
    output reg                  s_axi_awready,

    input  [C_AXIL_DATA_WIDTH-1:0] s_axi_wdata,
    input                       s_axi_wvalid,
    output reg                  s_axi_wready,

    output reg [1:0]            s_axi_bresp,
    output reg                  s_axi_bvalid,
    input                       s_axi_bready,

    input   [C_AXIL_ADDR_WIDTH-1:0] s_axi_araddr, 
    input                       s_axi_arvalid,
    output reg                  s_axi_arready,

    output reg [C_AXIL_DATA_WIDTH-1:0] s_axi_rdata,
    output reg [1:0]            s_axi_rresp,
    output reg                  s_axi_rvalid,
    input                       s_axi_rready,

    // AXI - Stream Master Interface
    output reg [C_AXIL_DATA_WIDTH-1:0] m_axis_tdata,
    output reg                    m_axis_tvalid,
    input                         m_axis_tready
);


    //Address map for these registers

    // 0x00 - start_reg
    // 0x04 - stop_reg
    // 0x08 - seed_reg
    // 0x0C - taps_reg

    // Registers
    reg start_reg;
    reg stop_reg;
    reg [7:0] seed_reg;
    reg [7:0] taps_reg;

    wire [7:0] lfsr_out;

    reg awhandshake;
    reg [C_AXIL_ADDR_WIDTH-1:0] awreg;

    always @(posedge aclk) begin
        if (!aresetn) begin
            s_axi_awready <= 1'b0;
            s_axi_wready <= 1'b0;
            s_axi_bvalid <= 1'b0;

            start_reg <= 1'b0;
            stop_reg <= 1'b0;
            seed_reg <= 8'h00;
            taps_reg <= 8'h00;

            awhandshake <= 1'b0;
            awreg <= 4'h0;
        end else begin  //this circuit is completed in 1 cycle always. So slave is always ready. otherwise  WREADY <= slave_is_ready; 
            s_axi_arready <= 1'b1;
            s_axi_awready <= 1'b1;
            s_axi_wready <= 1'b1;
        end
            

        if(s_axi_wvalid && s_axi_wready) begin  
            if (awhandshake) begin  //If aw handshake happened before
                case (awreg)
                    4'h0: start_reg <= s_axi_wdata[0];
                    4'h4: stop_reg <= s_axi_wdata[0];
                    4'h8: seed_reg <= s_axi_wdata[7:0];
                    4'hC: taps_reg <= s_axi_wdata[7:0];
                endcase
                awhandshake <= 1'b0;
                s_axi_bvalid <= 1'b1;  
                case(awreg)
                    4'h0, 4'h4, 4'h8, 4'hC: s_axi_bresp <= 2'b00; //OKAY
                    default: s_axi_bresp <= 2'b11; //SLVERR
                endcase          
            end
            else if(s_axi_awvalid && s_axi_awready) begin  //If aw handshake didn't happen
                case (s_axi_awaddr)
                    4'h0: start_reg <= s_axi_wdata[0];
                    4'h4: stop_reg <= s_axi_wdata[0];
                    4'h8: seed_reg <= s_axi_wdata[7:0];
                    4'hC: taps_reg <= s_axi_wdata[7:0];
                endcase
                awhandshake <= 1'b0;
                s_axi_bvalid <= 1'b1;
                case(s_axi_awaddr)
                    4'h0, 4'h4, 4'h8, 4'hC: s_axi_bresp <= 2'b00; //OKAY
                    default: s_axi_bresp <= 2'b11; //SLVERR
                endcase
            end
        end else if(s_axi_awvalid && s_axi_awready) begin //If aw handshake happened but data didn't come yet
            awhandshake <= 1'b1;
            awreg <= s_axi_awaddr;
        end
        if(s_axi_bvalid && s_axi_bready) begin
                s_axi_bvalid <= 1'b0;    
        end
    end

    always @(posedge aclk) begin
        if(!aresetn) begin
            s_axi_rvalid <= 1'b0;
            s_axi_rresp <= 2'b00;
            s_axi_rdata <= 32'b0;
            s_axi_arready <= 1'b0;
        end else begin
            s_axi_arready <= 1'b1;
        end
        if(s_axi_arvalid && s_axi_arready) begin
            s_axi_rdata <= {24'b0,lfsr_out};  //Only 1 output, so araddr is not required
            s_axi_rvalid <= 1'b1;
        end
        if(s_axi_rvalid && s_axi_rready) begin
            s_axi_rresp <= 2'b00; //OKAY
            s_axi_rvalid <= 1'b0; 
        end
    end
    
    
    always @(posedge aclk) begin
        if(!aresetn) begin
        // m_axis_tvalid <= 1'b0;
        m_axis_tdata <= 32'b0;
        end
        if(start_reg & ~stop_reg ) m_axis_tvalid <= 1'b1;
        else m_axis_tvalid <= 1'b0;
        if(m_axis_tready && m_axis_tvalid) begin
            m_axis_tdata <= {24'b0,lfsr_out};
        end 
     end
    



    LFSR m_lfsr(
        .clk(aclk),
        .reset(aresetn),
        .start(start_reg),
        .stop(stop_reg),
        .seed(seed_reg),
        .taps(taps_reg),
        .lfsr_out(lfsr_out)
    );


endmodule

iris_axi/top.v
module top #(
    parameter C_AXIL_ADDR_WIDTH = 4,
    parameter C_AXIL_DATA_WIDTH = 32
)(
    input aclk,
    input aresetn,

    // AXI-Lite Slave Interface
    input  [C_AXIL_ADDR_WIDTH-1:0] s_axi_awaddr,
    input                       s_axi_awvalid,

    input  [C_AXIL_DATA_WIDTH-1:0] s_axi_wdata,
    input                       s_axi_wvalid,


    input                       s_axi_bready,

    input   [C_AXIL_ADDR_WIDTH-1:0] s_axi_araddr, 
    input                       s_axi_arvalid,


    input                       s_axi_rready
    
);

    wire                  s_axi_awready;
    wire                  s_axi_wready;
    wire [1:0]            s_axi_bresp;
    wire                  s_axi_bvalid;
    wire                  s_axi_arready;
    wire [C_AXIL_DATA_WIDTH-1:0] s_axi_rdata;
    wire [1:0]            s_axi_rresp;
    wire                  s_axi_rvalid;

    wire [C_AXIL_DATA_WIDTH-1:0] tdata1, tdata2;
    wire                    tvalid1,tvalid2;
    wire                     tready1, tready2;




s_axil m_lfsr(
    .aclk(aclk),
    .aresetn(aresetn),
    .s_axi_awaddr(s_axi_awaddr),
    .s_axi_awvalid(s_axi_awvalid),
    .s_axi_awready(s_axi_awready),
    .s_axi_wdata(s_axi_wdata),
    .s_axi_wvalid(s_axi_wvalid),
    .s_axi_wready(s_axi_wready),
    .s_axi_bresp(s_axi_bresp),
    .s_axi_bvalid(s_axi_bvalid),
    .s_axi_bready(s_axi_bready),
    .s_axi_araddr(s_axi_araddr),
    .s_axi_arvalid(s_axi_arvalid),
    .s_axi_arready(s_axi_arready),
    .s_axi_rdata(s_axi_rdata),
    .s_axi_rresp(s_axi_rresp),
    .s_axi_rvalid(s_axi_rvalid),
    .s_axi_rready(s_axi_rready),

    .m_axis_tdata(tdata1),
    .m_axis_tvalid(tvalid1),
    .m_axis_tready(tready1)
);
s_m_hist m_hist(
    .aclk(aclk),
    .aresetn(aresetn),
    .s_axis_tdata(tdata1),
    .s_axis_tvalid(tvalid1),
    .s_axis_tready(tready1),
    .m_axis_tdata(tdata2),
    .m_axis_tvalid(tvalid2),
    .m_axis_tready(tready2)
);

axi_ram m_ram(
    .aclk(aclk),
    .aresetn(aresetn),
    .s_axis_tdata(tdata2),
    .s_axis_tvalid(tvalid2),
    .s_axis_tready(tready2)
);
endmodule

iris_axi/top_tb.v
`timescale 1ns/1ns

module top_tb;

    parameter C_AXIL_ADDR_WIDTH = 4;
    parameter C_AXIL_DATA_WIDTH = 32;

    reg aclk;
    reg aresetn;

    // AXI-Lite Slave Interface
    reg  [C_AXIL_ADDR_WIDTH-1:0] s_axi_awaddr;
    reg                       s_axi_awvalid;

    reg  [C_AXIL_DATA_WIDTH-1:0] s_axi_wdata;
    reg                       s_axi_wvalid;


    reg                       s_axi_bready;

    reg   [C_AXIL_ADDR_WIDTH-1:0] s_axi_araddr; 
    reg                       s_axi_arvalid; 
    reg                       s_axi_rready; 
    reg                       s_axi_rvalid; 

    top m_top(
        .aclk(aclk),
        .aresetn(aresetn),
        .s_axi_awaddr(s_axi_awaddr),
        .s_axi_awvalid(s_axi_awvalid),
        .s_axi_wdata(s_axi_wdata),
        .s_axi_wvalid(s_axi_wvalid),
        .s_axi_bready(s_axi_bready),
        .s_axi_araddr(s_axi_araddr),
        .s_axi_arvalid(s_axi_arvalid),
        .s_axi_rready(s_axi_rready)
    );
    
    initial begin aclk = 0;
    forever #5 aclk = ~aclk;
    end



    initial begin
    $dumpfile("top_tb.vcd");
    $dumpvars(0, top_tb);
    // $monitor("%h, %h, %h, %h, %h, %h, %h, %h",
    //     m_top.m_ram.mem[0],
    //     m_top.m_ram.mem[4],
    //     m_top.m_ram.mem[8],
    //     m_top.m_ram.mem[12],
    //     m_top.m_ram.mem[16],
    //     m_top.m_ram.mem[20],
    //     m_top.m_ram.mem[24],
    //     m_top.m_ram.mem[28]
    // );



    // 0x00 - start_reg
    // 0x04 - stop_reg
    // 0x08 - seed_reg
    // 0x0C - taps_reg


    $monitor("time %5d no %h %d, %d, %d, %d, %d, %d, %d, %d",
        $time,
                m_top.m_ram.number,
        m_top.m_hist.bin[0],
        m_top.m_hist.bin[1],
        m_top.m_hist.bin[2],
        m_top.m_hist.bin[3],
        m_top.m_hist.bin[4],
        m_top.m_hist.bin[5],
        m_top.m_hist.bin[6],
        m_top.m_hist.bin[7]
    );

    //     $monitor(" %h  ",
    //     m_top.m_ram.number
    // );


    aresetn <= 0;
    #10 aresetn <=1;
    s_axi_awaddr <= 0;
    s_axi_awvalid <= 0;
    s_axi_wdata <= 0;
    s_axi_wvalid <= 0;
    s_axi_araddr <= 0; 
    s_axi_arvalid <= 0;
    s_axi_araddr <= 0; 
    s_axi_arvalid <= 0;

    s_axi_rready <= 1;

    s_axi_bready <= 1;

    #10  s_axi_awaddr <= 32'h08;
    s_axi_awvalid <= 1;

    s_axi_wdata <= 32'h1D;
    s_axi_wvalid <= 1;

     #10  s_axi_awaddr <= 32'h0C;
    s_axi_awvalid <= 1;

    s_axi_wdata <= 32'h1D;
    s_axi_wvalid <= 1;

    #10  s_axi_awaddr <= 32'h04;
    s_axi_awvalid <= 1;

    s_axi_wdata <= 32'h01;
    s_axi_wvalid <= 1;



    #10  s_axi_awaddr <= 32'h00;
    s_axi_awvalid <= 1;

    s_axi_wdata <= 32'h01;
    s_axi_wvalid <= 1;

    #10  s_axi_awaddr <= 32'h04;
    s_axi_awvalid <= 1;

    s_axi_wdata <= 32'h00;
    s_axi_wvalid <= 1;

    #10 s_axi_araddr <= 32'h00;
    s_axi_arvalid <= 1;
    s_axi_rready <= 1;
    

    
    #3000 $finish;

    end
    
endmodule 


    // initial begin
    //     $dumpfile("top_tb.vcd");
    //     $dumpvars(0, top_tb);
    //     $monitor("%h, %h, %h, %h, %h, %h, %h, %h",
    //         m_top.m_ram.mem[0],
    //         m_top.m_ram.mem[1],
    //         m_top.m_ram.mem[2],
    //         m_top.m_ram.mem[3],
    //         m_top.m_ram.mem[4],
    //         m_top.m_ram.mem[5],
    //         m_top.m_ram.mem[6],
    //         m_top.m_ram.mem[7]
    //     );
    //     aclk = 0;
    //     aresetn = 0;
    //     s_axi_awaddr = 0;
    //     s_axi_awvalid = 0;
    //     s_axi_wdata = 0;
    //     s_axi_wvalid = 0;
    //     s_axi_bready = 0;
    //     s_axi_araddr = 0;
    //     s_axi_arvalid = 0;
    //     s_axi_rready = 0;

    //     #50 aresetn = 1;

    //     // Test the AXI-Lite interface

    //     #50 s_axi_awaddr <= 4'h8; // Address of seed_reg
    //     s_axi_awvalid <= 1'b1;
    //     s_axi_wdata <= 32'h69; // Write value to seed_reg
    //     s_axi_wvalid <= 1'b1;
    //     #50 s_axi_wvalid <= 1'b0;
    //      s_axi_awvalid <= 1'b0;



    //     #50 s_axi_awaddr = 4'hC; // Address of taps_reg
    //     s_axi_awvalid = 1'b1;
    //     s_axi_wdata = 32'h11D; // Write value to taps_reg
    //     s_axi_wvalid = 1'b1;
    //     #50 s_axi_wvalid = 1'b0;
    //     #50 s_axi_awvalid = 1'b0;
    //     #50 s_axi_bready = 1'b1; // Read response
    //         #50 s_axi_bready = 1'b0;

    //     #50 s_axi_awaddr = 4'h0; // Address of start_reg
    //         s_axi_awvalid = 1'b1;
    //         #50 s_axi_awvalid = 1'b0;

    //     #50 s_axi_wdata = 32'h00000001; // Write value to start_reg
    //         s_axi_wvalid = 1'b1;
    //         #50 s_axi_wvalid = 1'b0;

    //     #50 s_axi_bready = 1'b1; // Read response
    //         #50 s_axi_bready = 1'b0;

    // end

iris_axi/top_tb.vcd
$date
	Thu Apr  3 23:33:25 2025
$end
$version
	Icarus Verilog
$end
$timescale
	1ns
$end
$scope module top_tb $end
$var parameter 32 ! C_AXIL_ADDR_WIDTH $end
$var parameter 32 " C_AXIL_DATA_WIDTH $end
$var reg 1 # aclk $end
$var reg 1 $ aresetn $end
$var reg 4 % s_axi_araddr [3:0] $end
$var reg 1 & s_axi_arvalid $end
$var reg 4 ' s_axi_awaddr [3:0] $end
$var reg 1 ( s_axi_awvalid $end
$var reg 1 ) s_axi_bready $end
$var reg 1 * s_axi_rready $end
$var reg 32 + s_axi_wdata [31:0] $end
$var reg 1 , s_axi_wvalid $end
$scope module m_top $end
$var wire 1 # aclk $end
$var wire 1 $ aresetn $end
$var wire 4 - s_axi_araddr [3:0] $end
$var wire 1 & s_axi_arvalid $end
$var wire 4 . s_axi_awaddr [3:0] $end
$var wire 1 ( s_axi_awvalid $end
$var wire 1 ) s_axi_bready $end
$var wire 1 * s_axi_rready $end
$var wire 32 / s_axi_wdata [31:0] $end
$var wire 1 , s_axi_wvalid $end
$var wire 1 0 tvalid2 $end
$var wire 1 1 tvalid1 $end
$var wire 1 2 tready2 $end
$var wire 1 3 tready1 $end
$var wire 32 4 tdata2 [31:0] $end
$var wire 32 5 tdata1 [31:0] $end
$var wire 1 6 s_axi_wready $end
$var wire 1 7 s_axi_rvalid $end
$var wire 2 8 s_axi_rresp [1:0] $end
$var wire 32 9 s_axi_rdata [31:0] $end
$var wire 1 : s_axi_bvalid $end
$var wire 2 ; s_axi_bresp [1:0] $end
$var wire 1 < s_axi_awready $end
$var wire 1 = s_axi_arready $end
$var parameter 32 > C_AXIL_ADDR_WIDTH $end
$var parameter 32 ? C_AXIL_DATA_WIDTH $end
$scope module m_hist $end
$var wire 1 # aclk $end
$var wire 1 $ aresetn $end
$var wire 1 1 s_axis_tvalid $end
$var wire 32 @ s_axis_tdata [31:0] $end
$var wire 1 2 m_axis_tready $end
$var reg 8 A count [7:0] $end
$var reg 3 B count_bin [2:0] $end
$var reg 9 C data_bin [8:0] $end
$var reg 32 D m_axis_tdata [31:0] $end
$var reg 1 0 m_axis_tvalid $end
$var reg 8 E number [7:0] $end
$var reg 1 3 s_axis_tready $end
$var integer 32 F i [31:0] $end
$upscope $end
$scope module m_lfsr $end
$var wire 1 # aclk $end
$var wire 1 $ aresetn $end
$var wire 1 3 m_axis_tready $end
$var wire 4 G s_axi_araddr [3:0] $end
$var wire 1 & s_axi_arvalid $end
$var wire 4 H s_axi_awaddr [3:0] $end
$var wire 1 ( s_axi_awvalid $end
$var wire 1 ) s_axi_bready $end
$var wire 1 * s_axi_rready $end
$var wire 32 I s_axi_wdata [31:0] $end
$var wire 1 , s_axi_wvalid $end
$var wire 8 J lfsr_out [7:0] $end
$var parameter 32 K C_AXIL_ADDR_WIDTH $end
$var parameter 32 L C_AXIL_DATA_WIDTH $end
$var reg 1 M awhandshake $end
$var reg 4 N awreg [3:0] $end
$var reg 32 O m_axis_tdata [31:0] $end
$var reg 1 1 m_axis_tvalid $end
$var reg 1 = s_axi_arready $end
$var reg 1 < s_axi_awready $end
$var reg 2 P s_axi_bresp [1:0] $end
$var reg 1 : s_axi_bvalid $end
$var reg 32 Q s_axi_rdata [31:0] $end
$var reg 2 R s_axi_rresp [1:0] $end
$var reg 1 7 s_axi_rvalid $end
$var reg 1 6 s_axi_wready $end
$var reg 8 S seed_reg [7:0] $end
$var reg 1 T start_reg $end
$var reg 1 U stop_reg $end
$var reg 8 V taps_reg [7:0] $end
$scope module m_lfsr $end
$var wire 8 W a [1:8] $end
$var wire 1 # clk $end
$var wire 8 X lfsr_out [7:0] $end
$var wire 1 $ reset $end
$var wire 8 Y seed [7:0] $end
$var wire 1 T start $end
$var wire 1 U stop $end
$var wire 8 Z taps [1:8] $end
$var wire 1 [ feedback $end
$var reg 8 \ regs [1:8] $end
$upscope $end
$upscope $end
$scope module m_ram $end
$var wire 1 # aclk $end
$var wire 1 $ aresetn $end
$var wire 32 ] s_axis_tdata [31:0] $end
$var wire 1 0 s_axis_tvalid $end
$var wire 1 ^ ready $end
$var reg 8 _ count [7:0] $end
$var reg 3 ` count_bin [2:0] $end
$var reg 9 a data_bin [8:0] $end
$var reg 8 b number [7:0] $end
$var reg 1 2 s_axis_tready $end
$var integer 32 c i [31:0] $end
$upscope $end
$upscope $end
$upscope $end
$enddefinitions $end
$comment Show the parameter values. $end
$dumpall
b100000 L
b100 K
b100000 ?
b100 >
b100000 "
b100 !
$end
#0
$dumpvars
bx c
bx b
bx a
bx `
bx _
x^
bx ]
bx \
x[
bx Z
bx Y
bx X
bx W
bx V
xU
xT
bx S
bx R
bx Q
bx P
bx O
bx N
xM
bx J
bx I
bx H
bx G
bx F
bx E
bx D
bx C
bx B
bx A
bx @
x=
x<
bx ;
x:
bx 9
bx 8
x7
x6
bx 5
bx 4
x3
x2
x1
x0
bx /
bx .
bx -
x,
bx +
x*
x)
x(
bx '
x&
bx %
0$
0#
$end
#5
0[
b0 W
b0 N
0M
b0 V
b0 Z
b0 S
b0 Y
0U
0T
0:
06
0<
0=
b0 9
b0 Q
b0 8
b0 R
07
01
b0 5
b0 @
b0 O
b0 C
b0 B
b0 A
b0 4
b0 D
b0 ]
00
12
b0 a
b0 `
1^
b0 _
b0 b
b1000 F
b100100000 c
1#
#10
1)
1*
0&
b0 %
b0 -
b0 G
0,
b0 +
b0 /
b0 I
0(
b0 '
b0 .
b0 H
1$
0#
#15
13
16
1<
1=
1#
#20
1,
b11101 +
b11101 /
b11101 I
1(
b1000 '
b1000 .
b1000 H
0#
#25
b0 ;
b0 P
1:
b11101 S
b11101 Y
1#
#30
b1100 '
b1100 .
b1100 H
0#
#35
x[
b0xxx0x W
0:
b11101 V
b11101 Z
1#
#40
b1 +
b1 /
b1 I
b100 '
b100 .
b100 H
0#
#45
1:
1U
1#
#50
b0 '
b0 .
b0 H
0#
#55
0[
b11101 W
0:
1T
b11101 J
b11101 X
b11101 \
1#
#60
b0 +
b0 /
b0 I
b100 '
b100 .
b100 H
0#
#65
1:
0U
1#
#70
1&
0#
#75
b1100 W
11
17
b11101 9
b11101 Q
0:
b1110 J
b1110 X
b1110 \
1#
#80
0#
#85
b101 W
b111 J
b111 X
b111 \
1:
07
b1110 9
b1110 Q
b1110 5
b1110 @
b1110 O
b0 E
10
1#
#90
0#
#95
1[
b1 W
b1110 E
b111 5
b111 @
b111 O
17
b111 9
b111 Q
0:
b11 J
b11 X
b11 \
1#
#100
0#
#105
b100000 C
b1 A
b10000001 J
b10000001 X
b10000001 \
1:
07
b11 9
b11 Q
b11 5
b11 @
b11 O
b111 E
b111000000000000000000000 4
b111000000000000000000000 D
b111000000000000000000000 ]
1#
#110
0#
#115
0[
b0 W
b100001 C
b10 A
b1110 b
b11100000001000000100000 4
b11100000001000000100000 D
b11100000001000000100000 ]
b11 E
b10000001 5
b10000001 @
b10000001 O
17
b10000001 9
b10000001 Q
0:
b11000000 J
b11000000 X
b11000000 \
1#
#120
0#
#125
b100010 C
b11 A
b1100000 J
b1100000 X
b1100000 \
1:
07
b11000000 9
b11000000 Q
b11000000 5
b11000000 @
b11000000 O
b10000001 E
b1100000010000000100001 4
b1100000010000000100001 D
b1100000010000000100001 ]
b111 b
b1 _
b100000 a
1#
#130
0#
#135
1[
b10000 W
b10100000 C
b100 B
b1 A
b11 b
b10 _
b100001 a
b1000000100000011000000100010 4
b1000000100000011000000100010 D
b1000000100000011000000100010 ]
b11000000 E
b1100000 5
b1100000 @
b1100000 O
17
b1100000 9
b1100000 Q
0:
b110000 J
b110000 X
b110000 \
1#
#140
0#
#145
0[
b11000 W
b11000000 C
b101 B
b10011000 J
b10011000 X
b10011000 \
1:
07
b110000 9
b110000 Q
b110000 5
b110000 @
b110000 O
b1100000 E
b1100000000000001100010100000 4
b1100000000000001100010100000 D
b1100000000000001100010100000 ]
b10000001 b
b11 _
b100010 a
1#
#150
0#
#155
b1100 W
b1100000 C
b10 B
b11000000 b
b1 _
b100 `
b10100000 a
b110000000000001101011000000 4
b110000000000001101011000000 D
b110000000000001101011000000 ]
b110000 E
b10011000 5
b10011000 @
b10011000 O
17
b10011000 9
b10011000 Q
0:
b1001100 J
b1001100 X
b1001100 \
1#
#160
0#
#165
1[
b100 W
b1000000 C
b1 B
b100110 J
b100110 X
b100110 \
1:
07
b1001100 9
b1001100 Q
b1001100 5
b1001100 @
b1001100 O
b10011000 E
b11000000000001010001100000 4
b11000000000001010001100000 D
b11000000000001010001100000 ]
b1100000 b
b101 `
b11000000 a
1#
#170
0#
#175
0[
b10001 W
b10100001 C
b100 B
b10 A
b110000 b
b10 `
b1100000 a
b1001100000000001001001000000 4
b1001100000000001001001000000 D
b1001100000000001001001000000 ]
b1001100 E
b100110 5
b100110 @
b100110 O
17
b100110 9
b100110 Q
0:
b10010011 J
b10010011 X
b10010011 \
1#
#180
0#
#185
b1001 W
b1100001 C
b10 B
b1001001 J
b1001001 X
b1001001 \
1:
07
b10010011 9
b10010011 Q
b10010011 5
b10010011 @
b10010011 O
b100110 E
b100110000000010100010100001 4
b100110000000010100010100001 D
b100110000000010100010100001 ]
b10011000 b
b1 `
b1000000 a
1#
#190
0#
#195
1[
b100 W
b1000001 C
b1 B
b1001100 b
b10 _
b100 `
b10100001 a
b10011000000010010001100001 4
b10011000000010010001100001 D
b10011000000010010001100001 ]
b10010011 E
b1001001 5
b1001001 @
b1001001 O
17
b1001001 9
b1001001 Q
0:
b100100 J
b100100 X
b100100 \
1#
#200
0#
#205
b10000 W
b10100010 C
b100 B
b11 A
b10010010 J
b10010010 X
b10010010 \
1:
07
b100100 9
b100100 Q
b100100 5
b100100 @
b100100 O
b1001001 E
b1001001100000010001001000001 4
b1001001100000010001001000001 D
b1001001100000010001001000001 ]
b100110 b
b10 `
b1100001 a
1#
#210
0#
#215
0[
b1001 W
b1100010 C
b10 B
b10010011 b
b1 `
b1000001 a
b100100100000011100010100010 4
b100100100000011100010100010 D
b100100100000011100010100010 ]
b100100 E
b10010010 5
b10010010 @
b10010010 O
17
b10010010 9
b10010010 Q
0:
b11001001 J
b11001001 X
b11001001 \
1#
#220
0#
